nxsuite/__init__.py
nxsuite/nca.py
nxsuite/nsp.py
nxsuite/setup.py
nxsuite/tik.py
nxsuite/utils.py
nxsuite/_libs/hacpack.dll
nxsuite/_libs/hactool.dll
nxsuite-0.1.0.dist-info/LICENSE
nxsuite-0.1.0.dist-info/METADATA
nxsuite-0.1.0.dist-info/WHEEL
nxsuite-0.1.0.dist-info/top_level.txt
nxsuite-0.1.0.dist-info/RECORD
