Metadata-Version: 2.1
Name: nxsuite
Version: 0.1.0
Summary: NXSuite is a tool for editing various Nintendo Switch file formats.
Author: Vidpic
License: MIT License
Project-URL: Repository, https://github.com/Vidpic/nxsuite
Project-URL: Issues, https://github.com/Vidpic/nxsuite/issues
Classifier: Programming Language :: Python :: 3
Classifier: Programming Language :: Python :: 3.9
Classifier: License :: OSI Approved :: MIT License
Classifier: Operating System :: Microsoft :: Windows
Requires-Python: >=3.9
License-File: LICENSE
